[{
  "_id": {
    "$oid": "69fc2ea10d76f6d9df0ac4fa"
  },
  "name": "Zebronics V20",
  "type": "Electronics",
  "category": "Home Theatre",
  "price": 20000,
  "spec": 5.1
},
{
  "_id": {
    "$oid": "69fc31770d76f6d9df0ac4fb"
  },
  "name": "Dell Vostro",
  "type": "Electronics",
  "category": "Laptop",
  "price": 43000,
  "spec": [
    "corei5",
    "16GB",
    "512SSD"
  ]
},
{
  "_id": {
    "$oid": "69fc31770d76f6d9df0ac4fc"
  },
  "name": "Rebok Casual20",
  "type": "Footwear",
  "category": "Shoe",
  "price": 2500,
  "colors": [
    "red",
    "blue",
    "white"
  ]
},
{
  "_id": {
    "$oid": "69fc31770d76f6d9df0ac4fd"
  },
  "name": "Safari retro",
  "type": "Luggage",
  "price": 2900,
  "colors": [
    "teal",
    "red",
    "black"
  ]
}]